odoo/addons/commission_report_settlement_font_size/README.rst
odoo/addons/commission_report_settlement_font_size/__init__.py
odoo/addons/commission_report_settlement_font_size/__manifest__.py
odoo/addons/commission_report_settlement_font_size/report/report_settlement_document.xml
odoo/addons/commission_report_settlement_font_size/static/description/icon.png
odoo_addon_commission_report_settlement_font_size-15.0.1.0.0.2.dist-info/METADATA
odoo_addon_commission_report_settlement_font_size-15.0.1.0.0.2.dist-info/WHEEL
odoo_addon_commission_report_settlement_font_size-15.0.1.0.0.2.dist-info/top_level.txt
odoo_addon_commission_report_settlement_font_size-15.0.1.0.0.2.dist-info/RECORD
