Metadata-Version: 2.1
Name: odoo-addon-commission_report_settlement_font_size
Version: 15.0.1.0.0.2
Requires-Python: >=3.8
Requires-Dist: odoo-addon-commission>=15.0dev,<15.1dev
Requires-Dist: odoo>=15.0a,<15.1dev
Summary: Change the report settlement font size to 12px.
Home-page: https://github.com/sygel-technology/sy-commission
License: AGPL-3
Author: Sygel
Classifier: Programming Language :: Python
Classifier: Framework :: Odoo
Classifier: Framework :: Odoo :: 15.0
Classifier: License :: OSI Approved :: GNU Affero General Public License v3
